fleet/__init__.py
fleet/admin.py
fleet/app_settings.py
fleet/apps.py
fleet/auth_hooks.py
fleet/models.py
fleet/providers.py
fleet/tasks.py
fleet/tests.py
fleet/urls.py
fleet/utils.py
fleet/views.py
fleet/migrations/0001_initial.py
fleet/migrations/0002_fleet_name.py
fleet/migrations/0003_fleet_groups.py
fleet/migrations/0004_fleetinformation.py
fleet/migrations/__init__.py
fleet/static/fleet/libs/multi-select/0.9.12/css/multi-select.min.css
fleet/static/fleet/libs/slim-select/1.26.0/css/slimselect.min.css
fleet/static/fleet/libs/slim-select/1.26.0/js/slimselect.min.js
fleet/templates/fleet/base.html
fleet/templates/fleet/create_fleet.html
fleet/templates/fleet/dashboard.html
fleet/templates/fleet/edit_fleet.html
fleet/templates/fleet/fleet_details.html
fleet/templates/fleet/join_fleet.html
fleet/templates/fleet/bundles/multi-select-css.html
fleet/templates/fleet/bundles/slim-select-css.html
fleet/templates/fleet/bundles/slim-select-js.html
aa_fleet-1.2.0.dist-info/LICENSE
aa_fleet-1.2.0.dist-info/METADATA
aa_fleet-1.2.0.dist-info/WHEEL
aa_fleet-1.2.0.dist-info/top_level.txt
aa_fleet-1.2.0.dist-info/RECORD
