Metadata-Version: 2.1
Name: aa-fleet
Version: 1.2.0
Summary: Fleet plugin for Alliance Auth
Home-page: https://github.com/Dreadbomb/aa-fleet
Author: Crashtec
Author-email: huideaki@gmail.com
License: MIT
Platform: UNKNOWN
Classifier: Environment :: Web Environment
Classifier: Framework :: Django
Classifier: Framework :: Django :: 2.2
Classifier: Framework :: Django :: 3.1
Classifier: Intended Audience :: Developers
Classifier: License :: OSI Approved :: MIT License
Classifier: Operating System :: OS Independent
Classifier: Programming Language :: Python
Classifier: Programming Language :: Python :: 3.6
Classifier: Programming Language :: Python :: 3.7
Classifier: Programming Language :: Python :: 3.8
Classifier: Topic :: Internet :: WWW/HTTP
Classifier: Topic :: Internet :: WWW/HTTP :: Dynamic Content
Requires-Python: ~=3.6
Requires-Dist: allianceauth (>=2.7.3)
